aly/__init__.py
aly/bot.py
aly/cli.py
aly/management/__init__.py
aly/management/builder.py
aly/management/paraser.py
aly/management/structure/__init__.py
aly/management/structure/app.py
aly/management/structure/manage.py
aly/management/structure/new_bot.py
aly/management/structure/settings.py
aly-0.0.2.dist-info/LICENCE
aly-0.0.2.dist-info/METADATA
aly-0.0.2.dist-info/WHEEL
aly-0.0.2.dist-info/entry_points.txt
aly-0.0.2.dist-info/top_level.txt
aly-0.0.2.dist-info/RECORD
